peach_collector/__init__.py
peach_collector/__version__.py
peach_collector/_collector.py
peach_collector/_queue.py
peach_collector/_utils.py
tests/__init__.py
tests/test_collector.py
tests/test_queue.py
tests/test_utils.py
peach_collector-1.1.6.dist-info/METADATA
peach_collector-1.1.6.dist-info/WHEEL
peach_collector-1.1.6.dist-info/top_level.txt
peach_collector-1.1.6.dist-info/RECORD
