Metadata-Version: 2.1
Name: peach-collector
Version: 1.1.6
Summary: Peach Collector client library for Python
Home-page: https://git.ebu.io/now/peach-collector-py
Author: Matti Kotsalainen
Author-email: kotsalainen@ebu.ch
License: UNKNOWN
Platform: UNKNOWN
Classifier: Programming Language :: Python :: 3
Classifier: License :: OSI Approved :: MIT License
Classifier: Operating System :: OS Independent
Requires-Python: >=3.8
Requires-Dist: aioredis (==2.0.1)
Requires-Dist: httpx (==0.18.2)
Requires-Dist: orjson (==3.6.1)
